anemoi/datasets/__init__.py
anemoi/datasets/__main__.py
anemoi/datasets/_version.py
anemoi/datasets/check.py
anemoi/datasets/grids.py
anemoi/datasets/testing.py
anemoi/datasets/commands/__init__.py
anemoi/datasets/commands/check.py
anemoi/datasets/commands/cleanup.py
anemoi/datasets/commands/compare-lam.py
anemoi/datasets/commands/compare.py
anemoi/datasets/commands/copy.py
anemoi/datasets/commands/create.py
anemoi/datasets/commands/finalise-additions.py
anemoi/datasets/commands/finalise.py
anemoi/datasets/commands/grib-index.py
anemoi/datasets/commands/init-additions.py
anemoi/datasets/commands/init.py
anemoi/datasets/commands/inspect.py
anemoi/datasets/commands/load-additions.py
anemoi/datasets/commands/load.py
anemoi/datasets/commands/patch.py
anemoi/datasets/commands/publish.py
anemoi/datasets/commands/scan.py
anemoi/datasets/compute/__init__.py
anemoi/datasets/compute/recentre.py
anemoi/datasets/create/__init__.py
anemoi/datasets/create/check.py
anemoi/datasets/create/chunks.py
anemoi/datasets/create/config.py
anemoi/datasets/create/filter.py
anemoi/datasets/create/patch.py
anemoi/datasets/create/persistent.py
anemoi/datasets/create/size.py
anemoi/datasets/create/source.py
anemoi/datasets/create/typing.py
anemoi/datasets/create/utils.py
anemoi/datasets/create/writer.py
anemoi/datasets/create/zarr.py
anemoi/datasets/create/input/__init__.py
anemoi/datasets/create/input/action.py
anemoi/datasets/create/input/concat.py
anemoi/datasets/create/input/context.py
anemoi/datasets/create/input/data_sources.py
anemoi/datasets/create/input/empty.py
anemoi/datasets/create/input/filter.py
anemoi/datasets/create/input/function.py
anemoi/datasets/create/input/join.py
anemoi/datasets/create/input/misc.py
anemoi/datasets/create/input/pipe.py
anemoi/datasets/create/input/repeated_dates.py
anemoi/datasets/create/input/result.py
anemoi/datasets/create/input/step.py
anemoi/datasets/create/input/template.py
anemoi/datasets/create/input/trace.py
anemoi_datasets-0.5.26.dist-info/licenses/LICENSE
anemoi_datasets-0.5.26.dist-info/METADATA
anemoi_datasets-0.5.26.dist-info/WHEEL
anemoi_datasets-0.5.26.dist-info/entry_points.txt
anemoi_datasets-0.5.26.dist-info/top_level.txt
anemoi_datasets-0.5.26.dist-info/RECORD
