Metadata-Version: 2.4
Name: anemoi-datasets
Version: 0.5.26
Summary: A package to hold various functions to support training of ML models on ECMWF data.
Author-email: "European Centre for Medium-Range Weather Forecasts (ECMWF)" <software.support@ecmwf.int>
License:                                  Apache License
Project-URL: Changelog, https://github.com/ecmwf/anemoi-datasets/CHANGELOG.md
Project-URL: Documentation, https://anemoi-datasets.readthedocs.io/
Project-URL: Homepage, https://github.com/ecmwf/anemoi-datasets/
Project-URL: Issues, https://github.com/ecmwf/anemoi-datasets/issues
Project-URL: Repository, https://github.com/ecmwf/anemoi-datasets/
Keywords: ai,datasets,tools
Classifier: Development Status :: 4 - Beta
Classifier: Intended Audience :: Developers
Classifier: License :: OSI Approved :: Apache Software License
Classifier: Operating System :: OS Independent
Classifier: Programming Language :: Python :: 3 :: Only
Classifier: Programming Language :: Python :: 3.9
Classifier: Programming Language :: Python :: 3.10
Classifier: Programming Language :: Python :: 3.11
Classifier: Programming Language :: Python :: 3.12
Classifier: Programming Language :: Python :: 3.13
Classifier: Programming Language :: Python :: Implementation :: CPython
Classifier: Programming Language :: Python :: Implementation :: PyPy
Requires-Python: >=3.9
License-File: LICENSE
Requires-Dist: anemoi-transform>=0.1.10
Requires-Dist: anemoi-utils[provenance]>=0.4.26
Requires-Dist: cfunits
Requires-Dist: numcodecs<0.16
Requires-Dist: numpy
Requires-Dist: pyyaml
Requires-Dist: semantic-version
Requires-Dist: tqdm
Requires-Dist: zarr<=2.18.4
Provides-Extra: all
Requires-Dist: anemoi-datasets[comparelam,create,remote,xarray]; extra == "all"
Provides-Extra: comparelam
Requires-Dist: prettytable; extra == "comparelam"
Requires-Dist: termcolor; extra == "comparelam"
Provides-Extra: create
Requires-Dist: cachetools; extra == "create"
Requires-Dist: earthkit-data[mars]>=0.14; extra == "create"
Requires-Dist: earthkit-geo>=0.3; extra == "create"
Requires-Dist: earthkit-meteo>=0.3; extra == "create"
Requires-Dist: eccodes>=2.39.1; extra == "create"
Requires-Dist: entrypoints; extra == "create"
Requires-Dist: pyproj>=3; extra == "create"
Provides-Extra: dev
Requires-Dist: anemoi-datasets[all,docs,tests]; extra == "dev"
Provides-Extra: docs
Requires-Dist: anemoi-datasets[all]; extra == "docs"
Requires-Dist: nbsphinx; extra == "docs"
Requires-Dist: pandoc; extra == "docs"
Requires-Dist: sphinx; extra == "docs"
Requires-Dist: sphinx-argparse; extra == "docs"
Requires-Dist: sphinx-rtd-theme; extra == "docs"
Provides-Extra: remote
Requires-Dist: boto3; extra == "remote"
Requires-Dist: requests; extra == "remote"
Provides-Extra: tests
Requires-Dist: anemoi-datasets[xarray]; extra == "tests"
Requires-Dist: pytest; extra == "tests"
Requires-Dist: pytest-xdist; extra == "tests"
Provides-Extra: xarray
Requires-Dist: adlfs; extra == "xarray"
Requires-Dist: gcsfs; extra == "xarray"
Requires-Dist: kerchunk; extra == "xarray"
Requires-Dist: pandas; extra == "xarray"
Requires-Dist: planetary-computer; extra == "xarray"
Requires-Dist: pystac-client; extra == "xarray"
Requires-Dist: s3fs; extra == "xarray"
Dynamic: license-file
